neat/__init__.py
neat/config.py
neat/database.py
neat/exceptions.py
neat/main.py
neat/models.py
neat/types.py
neat/utils.py
neat_llm-0.0.1.dist-info/METADATA
neat_llm-0.0.1.dist-info/WHEEL
neat_llm-0.0.1.dist-info/RECORD
