Metadata-Version: 2.3
Name: neat-llm
Version: 0.0.1
Summary: A simpler llm abstraction.
Requires-Python: >=3.8
Requires-Dist: instructor>=1.3.7
Requires-Dist: ipykernel>=6.29.5
Requires-Dist: litellm>=1.44.5
Requires-Dist: loguru>=0.7.2
Requires-Dist: pydantic-settings>=2.3.4
Requires-Dist: pydantic>=2.8.2
